img2wav.py
img2wav-0.1.2.dist-info/DESCRIPTION.rst
img2wav-0.1.2.dist-info/METADATA
img2wav-0.1.2.dist-info/RECORD
img2wav-0.1.2.dist-info/WHEEL
img2wav-0.1.2.dist-info/entry_points.txt
img2wav-0.1.2.dist-info/metadata.json
img2wav-0.1.2.dist-info/top_level.txt
