Metadata-Version: 2.0
Name: img2wav
Version: 0.1.2
Summary: Convert images to wav audio files to view in a spectrogram
Home-page: https://github.com/shareef12/img2wav
Author: Christian Sharpsten
Author-email: chris.sharpsten@gmail.com
License: GPL-2
Download-URL: https://github.com/shareef12/img2wav/archive/v0.1.2.tar.gz
Platform: UNKNOWN
Requires-Dist: Pillow
Requires-Dist: numpy
